rokas_data_manipulation/__init__.py
rokas_data_manipulation/convolution.py
rokas_data_manipulation/transpose.py
rokas_data_manipulation/window.py
tests/test_convolution.py
tests/test_transpose.py
tests/test_window.py
rokas_data_manipulation-0.1.4.dist-info/METADATA
rokas_data_manipulation-0.1.4.dist-info/WHEEL
rokas_data_manipulation-0.1.4.dist-info/RECORD
