Metadata-Version: 2.1
Name: rokas-data-manipulation
Version: 0.1.4
Summary: A package for common data manipulation operations in Python
Author: Rokas Galdikas
Author-email: rokas.galdikas@yahoo.com
Requires-Python: >=3.9,<4.0
Classifier: Programming Language :: Python :: 3
Classifier: Programming Language :: Python :: 3.9
Classifier: Programming Language :: Python :: 3.10
Classifier: Programming Language :: Python :: 3.11
Classifier: Programming Language :: Python :: 3.12
Requires-Dist: numpy (>=1.26.4,<2.0.0)
